LICENSE
README.md
pyproject.toml
setup.cfg
setup.py
pypleski/__init__.py
pypleski/aps.py
pypleski/certificate.py
pypleski/core.py
pypleski/customer.py
pypleski/database.py
pypleski/db_server.py
pypleski/dns.py
pypleski/error_handling.py
pypleski/extension.py
pypleski/ftp_user.py
pypleski/git.py
pypleski/ip.py
pypleski/locales.py
pypleski/log_rotation.py
pypleski/mail.py
pypleski/nodejs.py
pypleski/php_handlers.py
pypleski/reseller.py
pypleski/reseller_plan.py
pypleski/secret_key.py
pypleski/server.py
pypleski/service_plan.py
pypleski/service_plan_addon.py
pypleski/session.py
pypleski/site.py
pypleski/site_alias.py
pypleski/subdomain.py
pypleski/updater.py
pypleski/webspace.py
pypleski.egg-info/PKG-INFO
pypleski.egg-info/SOURCES.txt
pypleski.egg-info/dependency_links.txt
pypleski.egg-info/requires.txt
pypleski.egg-info/top_level.txt