Metadata-Version: 2.1
Name: pypleski
Version: 0.0.7
Summary: Simplified API to access the PLESK XML API
Home-page: https://codingcow.de/pypleski
Author: Uli Toll
Author-email: pypleski@codingcow.de
License: UNKNOWN
Platform: UNKNOWN
Classifier: Development Status :: 2 - Pre-Alpha
Classifier: Intended Audience :: Developers
Classifier: License :: OSI Approved :: GNU Lesser General Public License v3 (LGPLv3)
Classifier: Operating System :: POSIX :: Linux
Classifier: Programming Language :: Python :: 3.6
Classifier: Programming Language :: Python :: 3.7
Classifier: Programming Language :: Python :: 3.8
License-File: LICENSE
